{"title": "water purifier", "date": "28/08/2020 04:00:51", "best_item": {"asin": "B06XWW9HQK", "url": "http://www.amazon.in/dp/B06XWW9HQK", "title": "Nasaka Tulip N1 8-Litre RO+UF+ORPH Water Purifier", "seller": "Visit the NASAKA Store", "price": 7950.0}, "currency": "\u20b9", "filters": {"min": "8000", "max": "9000"}, "base_link": "http://www.amazon.in/", "products": [{"asin": "B07CJVRHSK", "url": "http://www.amazon.in/dp/B07CJVRHSK", "title": "Blue Star Aristo RO+UV AR4BLAM01 7-Litre Water Purifier", "seller": "Brand: Blue Star", "price": 8499.0}, {"asin": "B008LN6156", "url": "http://www.amazon.in/dp/B008LN6156", "title": "KENT Maxx 7-Litres Wall Mountable/Table Top UV + UF (White and Blue) 60-Ltr/hr Water Purifier with detachable storage tank", "seller": "Visit the KENT Store", "price": 8035.0}, {"asin": "B08BXDZCSS", "url": "http://www.amazon.in/dp/B08BXDZCSS", "title": "Aqua Active Misty RO+UV+UF+TDS controller 10-Litre Water Purifier, Black", "seller": "Brand: Aqua Active", "price": 8500.0}, {"asin": "B07V24P4K2", "url": "http://www.amazon.in/dp/B07V24P4K2", "title": "Faber Galaxy RO+UF+MAT, 9 Liters, 7 Stage Mineral Water Purifier with Upto 2500 TDS, White", "seller": "Visit the Faber Store", "price": 8498.0}, {"asin": "B079K3JTKT", "url": "http://www.amazon.in/dp/B079K3JTKT", "title": "Havells UV Plus 8-Litres UF Water Purifier (White/Sky Blue)", "seller": "Visit the Havells Store", "price": 8359.0}, {"asin": "B06XWW9HQK", "url": "http://www.amazon.in/dp/B06XWW9HQK", "title": "Nasaka Tulip N1 8-Litre RO+UF+ORPH Water Purifier", "seller": "Visit the NASAKA Store", "price": 7950.0}, {"asin": "B07FDZ9KL7", "url": "http://www.amazon.in/dp/B07FDZ9KL7", "title": "HUL Pureit Classic G2 Mineral RO+MF 6L Water Purifier", "seller": "Brand: HUL Pureit", "price": 8365.0}, {"asin": "B08BZTHS64", "url": "http://www.amazon.in/dp/B08BZTHS64", "title": "Faber Q-Wa Aquatron Ultra Plus RO +MAT+ Copper Guard, 10 Liters, 7 Stage Mineral Water Purifier with Upto 2500 TDS, White", "seller": "Visit the Faber Store", "price": 8800.0}, {"asin": "B075WT9C2Q", "url": "http://www.amazon.in/dp/B075WT9C2Q", "title": "Aqua Active RO+ UV + UF + MF Water Purifier - 15 Liters", "seller": "Brand: Aqua Active", "price": 8200.0}, {"asin": "B08BXDVCNC", "url": "http://www.amazon.in/dp/B08BXDVCNC", "title": "Aqua Active Misty RO+UV+ Megnectic Softner + TDS controller 10-Litre Water Purifier, Black", "seller": "Brand: Aqua Active", "price": 8500.0}, {"asin": "B089WBRVGC", "url": "http://www.amazon.in/dp/B089WBRVGC", "title": "(Renewed) A.O.Smith Z1 UV 10 Litre Wall Mountable, Table UV Black 10 Litre Water Purifier", "seller": "Visit the Amazon Renewed Store", "price": 8671.0}, {"asin": "B08BXD4HBK", "url": "http://www.amazon.in/dp/B08BXD4HBK", "title": "Aqua Active Misty RO+Alkaline 5 Stage Reverse Osmosis 10-Litre Water Purifier System with Ultraviolet Sterilizer, Black", "seller": "Brand: Aqua Active", "price": 8500.0}, {"asin": "B08FZPGDS7", "url": "http://www.amazon.in/dp/B08FZPGDS7", "title": "KRPLUS Misty Royal (RO+Alkaline+TDS) 6L Water Purifier,7 Stages of Purification (Black)", "seller": "Brand: KRPLUS", "price": 8499.0}]}